zoosrv
